LICENSE.md
README.md
setup.cfg
setup.py
NanoCETPy/__init__.py
NanoCETPy/__main__.py
NanoCETPy/_version.py
NanoCETPy/start_alignment.py
NanoCETPy/start_cam_feed.py
NanoCETPy/start_recording.py
NanoCETPy/start_sequential.py
NanoCETPy/alignment/__init__.py
NanoCETPy/alignment/controller/__init__.py
NanoCETPy/alignment/controller/lucamapi/__init__.py
NanoCETPy/alignment/controller/lucamapi/api.py
NanoCETPy/alignment/controller/lucamapi/camera.py
NanoCETPy/alignment/models/__init__.py
NanoCETPy/alignment/models/arduino.py
NanoCETPy/alignment/models/experiment.py
NanoCETPy/alignment/models/lumenera_model_draft.py
NanoCETPy/alignment/models/model_utils.py
NanoCETPy/alignment/views/__init__.py
NanoCETPy/alignment/views/cam_window.py
NanoCETPy/dispertech/__init__.py
NanoCETPy/dispertech/controllers/__init__.py
NanoCETPy/dispertech/controllers/arduino.py
NanoCETPy/dispertech/models/__init__.py
NanoCETPy/dispertech/models/arduino.py
NanoCETPy/recording/__init__.py
NanoCETPy/recording/models/__init__.py
NanoCETPy/recording/models/experiment.py
NanoCETPy/recording/models/movie_saver.py
NanoCETPy/recording/views/__init__.py
NanoCETPy/recording/views/recording_window.py
NanoCETPy/resources/Roboto-Regular.ttf
NanoCETPy/resources/config_default.yml
NanoCETPy/sequential/__init__.py
NanoCETPy/sequential/models/__init__.py
NanoCETPy/sequential/models/arduino.py
NanoCETPy/sequential/models/basler.py
NanoCETPy/sequential/models/demo.py
NanoCETPy/sequential/models/experiment.py
NanoCETPy/sequential/models/model_utils.py
NanoCETPy/sequential/models/movie_saver.py
NanoCETPy/sequential/views/ElectronicsTestingGUI.py
NanoCETPy/sequential/views/__init__.py
NanoCETPy/sequential/views/camera_viewer_widget.py
NanoCETPy/sequential/views/sequential_window.py
NanoCETPy/sequential/views/GUI/Close_Widget.ui
NanoCETPy/sequential/views/GUI/Focus_Widget.ui
NanoCETPy/sequential/views/GUI/Measurement_Widget - Copy.ui
NanoCETPy/sequential/views/GUI/Measurement_Widget.ui
nanocetpy.egg-info/PKG-INFO
nanocetpy.egg-info/SOURCES.txt
nanocetpy.egg-info/dependency_links.txt
nanocetpy.egg-info/entry_points.txt
nanocetpy.egg-info/requires.txt
nanocetpy.egg-info/top_level.txt